llm_ctx/__init__.py
llm_ctx/_modidx.py
llm_ctx/core.py
llm_ctx-0.0.1.dist-info/LICENSE
llm_ctx-0.0.1.dist-info/METADATA
llm_ctx-0.0.1.dist-info/WHEEL
llm_ctx-0.0.1.dist-info/entry_points.txt
llm_ctx-0.0.1.dist-info/top_level.txt
llm_ctx-0.0.1.dist-info/RECORD
